{
  "clock_end": "2026-03-31T23:59:59Z",
  "clock_start": "2026-01-01T00:00:00Z",
  "config_hash": "666019b2a7c3aaac3e6a2eb066abce7936537533f2abbe4ee134437ad9d15b59",
  "deliveries_by_event": {
    "account-activated:v1": 351,
    "account-funded:v1": 298,
    "application-submitted:v1": 402,
    "campaign-spend-recorded:v1": 25,
    "customer-outcome-recorded:v1": 24,
    "experiment-assigned:v1": 168,
    "kyc-decisioned:v1": 405,
    "referral-invited:v1": 52,
    "referral-qualified:v1": 24,
    "referral-qualified:v2": 19,
    "reward-booked:v1": 33,
    "reward-reversed:v1": 1,
    "reward-settled:v1": 31
  },
  "delivery_count": 1833,
  "expected_beyond_lookback": 11,
  "expected_duplicates": 18,
  "expected_late_arrivals": 74,
  "expected_quarantined": 9,
  "expected_reversals": 1,
  "freshness": {
    "breached": true,
    "delayed_deliveries": 77,
    "max_gap_hours": 102.3672,
    "outage_end": "2026-02-18T23:59:59Z",
    "outage_start": "2026-02-14T23:59:59Z",
    "threshold_hours": 72
  },
  "generator_version": "0.1.0",
  "lifecycle_end_states": {
    "ref_00aa78edf4": "invited",
    "ref_01fe363d37": "invited",
    "ref_03cce6281d": "invited",
    "ref_1193f66b67": "invited",
    "ref_15711be3ff": "settled",
    "ref_1b4ee14f3c": "settled",
    "ref_1ccf8cdc52": "invited",
    "ref_1d30de8c1a": "settled",
    "ref_1f98a60945": "settled",
    "ref_2bf1c52afc": "invited",
    "ref_2f6a6f3936": "invited",
    "ref_2fec54438b": "settled",
    "ref_315919991f": "settled",
    "ref_32b119c1e3": "settled",
    "ref_33b954d8c3": "settled",
    "ref_353cea4c98": "invited",
    "ref_364a6c77eb": "settled",
    "ref_36bcab9988": "settled",
    "ref_3cbca32324": "settled",
    "ref_4301a9c59f": "settled",
    "ref_5b38166323": "invited",
    "ref_5c3bec222f": "qualified",
    "ref_68bf776b7a": "settled",
    "ref_78d527d5d5": "invited",
    "ref_7933326de0": "settled",
    "ref_81cf611b98": "invited",
    "ref_8554ed8698": "settled",
    "ref_890680c011": "settled",
    "ref_90ed3cf1dc": "invited",
    "ref_9b635fd8b7": "settled",
    "ref_9efab0eb73": "invited",
    "ref_a4cb0f2d41": "settled",
    "ref_a866e2e388": "settled",
    "ref_ad3852709b": "invited",
    "ref_b563616ee4": "settled",
    "ref_b67cf0aa78": "reversed",
    "ref_ba01b0c908": "invited",
    "ref_babed37b34": "settled",
    "ref_bb81b29605": "settled",
    "ref_c86f6858f0": "settled",
    "ref_cecb7f8a63": "invited",
    "ref_dcf86419c4": "settled",
    "ref_e2905c1ece": "invited",
    "ref_e36d18a82e": "settled",
    "ref_e75d9f4d2c": "settled",
    "ref_e7957b27f3": "settled",
    "ref_eae73f1b60": "settled",
    "ref_ec45ed25cc": "settled",
    "ref_fa59146cb6": "invited",
    "ref_fad21985fd": "settled",
    "ref_ff836770f2": "settled"
  },
  "limitations": "Deterministic seeded generation with injected defects; no concurrency, no realistic timing distributions, no real-world calibration of failure rates. Engineering truth only (the synthetic-truth contract).",
  "profile": "tiny",
  "prohibited_interpretation": "Synthetic engineering benchmark only. Volumes, rates and amounts are generated for oracle coverage and carry no information about real customers, real funnels or Monzo.",
  "reconciliation": {
    "booked_minor": 160000,
    "entitled_minor": 165000,
    "exceptions": [
      {
        "count": 1,
        "reason": "missing_posting"
      }
    ],
    "outstanding_payable_minor": 0,
    "reversed_minor": 5000,
    "settled_minor": 155000
  },
  "schema_evolution": {
    "referral_qualified_v1": 24,
    "referral_qualified_v2": 19
  },
  "seed": 42,
  "sub_seeds": {
    "faults": "42:faults",
    "journeys": "42:journeys"
  },
  "unique_business_events": 1806
}
